{
    "header": {
        "dialogueInfo": {
            "dialogueID": "32cd0a2e-e1d5-587b-8514-aa38430ed344",
            "numberOfParticipants": 2,
            "numberOfUtterances": 19,
            "numberOfTurns": 7,
            "source": "한국어SNS",
            "single_topic": "개인 및 관계",
            "multi_topic": [
                "안부/일상_일상공유_소문/루머"
            ]
        },
        "participantsInfo": [
            {
                "participantID": "P01",
                "gender": "남성",
                "age": "20대",
                "residentialProvince": "서울특별시"
            },
            {
                "participantID": "P02",
                "gender": "여성",
                "age": "20대",
                "residentialProvince": "경기도"
            }
        ]
    },
    "body": [
        {
            "utteranceID": "U01",
            "turnID": "T01",
            "participantID": "P01",
            "date": "2014-09-22",
            "time": "22:50:00",
            "utterance": "#@이름# #@이름#"
        },
        {
            "utteranceID": "U02",
            "turnID": "T01",
            "participantID": "P01",
            "date": "2014-09-22",
            "time": "22:50:00",
            "utterance": "오늘 집에"
        },
        {
            "utteranceID": "U03",
            "turnID": "T01",
            "participantID": "P01",
            "date": "2014-09-22",
            "time": "22:50:00",
            "utterance": "여자온데"
        },
        {
            "utteranceID": "U04",
            "turnID": "T02",
            "participantID": "P02",
            "date": "2014-09-22",
            "time": "22:51:00",
            "utterance": "응?"
        },
        {
            "utteranceID": "U05",
            "turnID": "T02",
            "participantID": "P02",
            "date": "2014-09-22",
            "time": "22:51:00",
            "utterance": "머?"
        },
        {
            "utteranceID": "U06",
            "turnID": "T02",
            "participantID": "P02",
            "date": "2014-09-22",
            "time": "22:51:00",
            "utterance": "누구?"
        },
        {
            "utteranceID": "U07",
            "turnID": "T02",
            "participantID": "P02",
            "date": "2014-09-22",
            "time": "22:51:00",
            "utterance": "누가?"
        },
        {
            "utteranceID": "U08",
            "turnID": "T02",
            "participantID": "P02",
            "date": "2014-09-22",
            "time": "22:51:00",
            "utterance": "누가댈꼬오는데!!!!!!"
        },
        {
            "utteranceID": "U09",
            "turnID": "T03",
            "participantID": "P01",
            "date": "2014-09-22",
            "time": "22:51:00",
            "utterance": "ㅋㅋㅋㅋㅋ"
        },
        {
            "utteranceID": "U10",
            "turnID": "T03",
            "participantID": "P01",
            "date": "2014-09-22",
            "time": "22:51:00",
            "utterance": "#@이름#이가"
        },
        {
            "utteranceID": "U11",
            "turnID": "T03",
            "participantID": "P01",
            "date": "2014-09-22",
            "time": "22:51:00",
            "utterance": "#@이름#이 친구"
        },
        {
            "utteranceID": "U12",
            "turnID": "T03",
            "participantID": "P01",
            "date": "2014-09-22",
            "time": "22:51:00",
            "utterance": "누구라드라"
        },
        {
            "utteranceID": "U13",
            "turnID": "T03",
            "participantID": "P01",
            "date": "2014-09-22",
            "time": "22:51:00",
            "utterance": "몰라 여튼 ㅇㅇ"
        },
        {
            "utteranceID": "U14",
            "turnID": "T04",
            "participantID": "P02",
            "date": "2014-09-22",
            "time": "22:51:00",
            "utterance": "#@이름#이??"
        },
        {
            "utteranceID": "U15",
            "turnID": "T04",
            "participantID": "P02",
            "date": "2014-09-22",
            "time": "22:51:00",
            "utterance": "#@이름#이??"
        },
        {
            "utteranceID": "U16",
            "turnID": "T05",
            "participantID": "P01",
            "date": "2014-09-22",
            "time": "22:52:00",
            "utterance": "둘중하나지않을까"
        },
        {
            "utteranceID": "U17",
            "turnID": "T06",
            "participantID": "P02",
            "date": "2014-09-22",
            "time": "22:53:00",
            "utterance": "음....."
        },
        {
            "utteranceID": "U18",
            "turnID": "T06",
            "participantID": "P02",
            "date": "2014-09-22",
            "time": "22:53:00",
            "utterance": "나두갈래!!!!!!!!!"
        },
        {
            "utteranceID": "U19",
            "turnID": "T07",
            "participantID": "P01",
            "date": "2014-09-22",
            "time": "22:54:00",
            "utterance": "응???ㅋㅋㅋㅋ"
        }
    ]
}