{
    "header": {
        "dialogueInfo": {
            "dialogueID": "fdd1081c-08f7-5d7e-b36c-2dadb52d6e31",
            "numberOfParticipants": 3,
            "numberOfUtterances": 9,
            "numberOfTurns": 5,
            "multi_topic": [
                "안부/일상_일상공유_현재상태/행위"
            ],
            "source": "한국어SNS",
            "single_topic": "주거와 생활"
        },
        "participantsInfo": [
            {
                "participantID": "P01",
                "gender": "여성",
                "age": "20대",
                "residentialProvince": "서울특별시"
            },
            {
                "participantID": "P02",
                "gender": "여성",
                "age": "20대",
                "residentialProvince": "서울특별시"
            },
            {
                "participantID": "P03",
                "gender": "여성",
                "age": "20대",
                "residentialProvince": "서울특별시"
            }
        ]
    },
    "body": [
        {
            "utteranceID": "U01",
            "turnID": "T01",
            "participantID": "P01",
            "date": "2019-05-16",
            "time": "19:50:00",
            "utterance": "괜히"
        },
        {
            "utteranceID": "U02",
            "turnID": "T01",
            "participantID": "P01",
            "date": "2019-05-16",
            "time": "19:50:00",
            "utterance": "책"
        },
        {
            "utteranceID": "U03",
            "turnID": "T01",
            "participantID": "P01",
            "date": "2019-05-16",
            "time": "19:50:00",
            "utterance": "무겁다"
        },
        {
            "utteranceID": "U04",
            "turnID": "T02",
            "participantID": "P02",
            "date": "2019-05-16",
            "time": "20:51:00",
            "utterance": "마쟈"
        },
        {
            "utteranceID": "U05",
            "turnID": "T03",
            "participantID": "P03",
            "date": "2019-05-16",
            "time": "20:51:00",
            "utterance": "나도 독서실에 책 두고다니게"
        },
        {
            "utteranceID": "U06",
            "turnID": "T04",
            "participantID": "P01",
            "date": "2019-05-16",
            "time": "20:53:00",
            "utterance": "웅 ㅜㅠ넘무거"
        },
        {
            "utteranceID": "U07",
            "turnID": "T04",
            "participantID": "P01",
            "date": "2019-05-16",
            "time": "20:53:00",
            "utterance": "고생해"
        },
        {
            "utteranceID": "U08",
            "turnID": "T05",
            "participantID": "P03",
            "date": "2019-05-16",
            "time": "20:55:00",
            "utterance": "옹"
        },
        {
            "utteranceID": "U09",
            "turnID": "T05",
            "participantID": "P03",
            "date": "2019-05-16",
            "time": "20:55:00",
            "utterance": "하"
        }
    ]
}