{
    "header": {
        "dialogueInfo": {
            "dialogueID": "fe7da0db-5e7c-5df1-b193-bed88b157dcb",
            "numberOfParticipants": 4,
            "numberOfUtterances": 9,
            "numberOfTurns": 5,
            "multi_topic": [
                "안부/일상_일상공유_현재상태/행위",
                "생활/행사_특별생활_사적행사"
            ],
            "source": "한국어SNS",
            "single_topic": "행사"
        },
        "participantsInfo": [
            {
                "participantID": "P01",
                "gender": "여성",
                "age": "20대",
                "residentialProvince": "충청남도"
            },
            {
                "participantID": "P02",
                "gender": "여성",
                "age": "20대",
                "residentialProvince": "대전광역시"
            },
            {
                "participantID": "P03",
                "gender": "여성",
                "age": "20대",
                "residentialProvince": "대전광역시"
            },
            {
                "participantID": "P04",
                "gender": "여성",
                "age": "20대",
                "residentialProvince": "대전광역시"
            }
        ]
    },
    "body": [
        {
            "utteranceID": "U01",
            "turnID": "T01",
            "participantID": "P01",
            "date": "2019-08-12",
            "time": "12:26:00",
            "utterance": "한남대 스벅이"
        },
        {
            "utteranceID": "U02",
            "turnID": "T01",
            "participantID": "P01",
            "date": "2019-08-12",
            "time": "12:26:00",
            "utterance": "어디쯤에 있냐"
        },
        {
            "utteranceID": "U03",
            "turnID": "T01",
            "participantID": "P01",
            "date": "2019-08-12",
            "time": "12:26:00",
            "utterance": "나 진짜 거기까지 가는거 극악인데"
        },
        {
            "utteranceID": "U04",
            "turnID": "T01",
            "participantID": "P01",
            "date": "2019-08-12",
            "time": "12:26:00",
            "utterance": "마중나와주실분"
        },
        {
            "utteranceID": "U05",
            "turnID": "T02",
            "participantID": "P02",
            "date": "2019-08-12",
            "time": "12:31:00",
            "utterance": "#@시스템#사진#"
        },
        {
            "utteranceID": "U06",
            "turnID": "T02",
            "participantID": "P02",
            "date": "2019-08-12",
            "time": "12:31:00",
            "utterance": "여기임?"
        },
        {
            "utteranceID": "U07",
            "turnID": "T03",
            "participantID": "P03",
            "date": "2019-08-12",
            "time": "13:47:00",
            "utterance": "ㅇㅇㅇㅇㅇ"
        },
        {
            "utteranceID": "U08",
            "turnID": "T04",
            "participantID": "P04",
            "date": "2019-08-12",
            "time": "14:01:00",
            "utterance": "#@이름# 언제올꾸"
        },
        {
            "utteranceID": "U09",
            "turnID": "T05",
            "participantID": "P01",
            "date": "2019-08-12",
            "time": "14:02:00",
            "utterance": "아직 모르겟슴"
        }
    ]
}