{
    "header": {
        "dialogueInfo": {
            "dialogueID": "ffc8ec61-c649-50f3-9fb3-f97c518815bd",
            "numberOfParticipants": 2,
            "numberOfUtterances": 20,
            "numberOfTurns": 10,
            "source": "한국어SNS",
            "single_topic": "여가 생활",
            "multi_topic": [
                "안부/일상_일상공유_현재상태/행위"
            ]
        },
        "participantsInfo": [
            {
                "participantID": "P01",
                "gender": "남성",
                "age": "30대",
                "residentialProvince": "경상남도"
            },
            {
                "participantID": "P02",
                "gender": "남성",
                "age": "30대",
                "residentialProvince": "서울특별시"
            }
        ]
    },
    "body": [
        {
            "utteranceID": "U01",
            "turnID": "T01",
            "participantID": "P01",
            "date": "2018-10-06",
            "time": "18:48:00",
            "utterance": "저거 프로그램 켜놔도 누가 뺏어가는거 없제?"
        },
        {
            "utteranceID": "U02",
            "turnID": "T02",
            "participantID": "P02",
            "date": "2018-10-06",
            "time": "18:48:00",
            "utterance": "없어ㅋㅋㅋㅋㅋ"
        },
        {
            "utteranceID": "U03",
            "turnID": "T02",
            "participantID": "P02",
            "date": "2018-10-06",
            "time": "18:48:00",
            "utterance": "송금은"
        },
        {
            "utteranceID": "U04",
            "turnID": "T02",
            "participantID": "P02",
            "date": "2018-10-06",
            "time": "18:48:00",
            "utterance": "가능함"
        },
        {
            "utteranceID": "U05",
            "turnID": "T03",
            "participantID": "P01",
            "date": "2018-10-06",
            "time": "18:48:00",
            "utterance": "컴공과로써 분석해봐 ㅋㅋ"
        },
        {
            "utteranceID": "U06",
            "turnID": "T03",
            "participantID": "P01",
            "date": "2018-10-06",
            "time": "18:48:00",
            "utterance": "대받 아이디어"
        },
        {
            "utteranceID": "U07",
            "turnID": "T03",
            "participantID": "P01",
            "date": "2018-10-06",
            "time": "18:48:00",
            "utterance": "우리 피씨 할때 생각났는데"
        },
        {
            "utteranceID": "U08",
            "turnID": "T03",
            "participantID": "P01",
            "date": "2018-10-06",
            "time": "18:49:00",
            "utterance": "학교같은데 컴터실에"
        },
        {
            "utteranceID": "U09",
            "turnID": "T03",
            "participantID": "P01",
            "date": "2018-10-06",
            "time": "18:49:00",
            "utterance": "다 돌려놔두면"
        },
        {
            "utteranceID": "U10",
            "turnID": "T03",
            "participantID": "P01",
            "date": "2018-10-06",
            "time": "18:49:00",
            "utterance": "컴터 잘 안끄잖아"
        },
        {
            "utteranceID": "U11",
            "turnID": "T04",
            "participantID": "P02",
            "date": "2018-10-06",
            "time": "18:49:00",
            "utterance": "이거 웹에 로그인만안해놓으면됨"
        },
        {
            "utteranceID": "U12",
            "turnID": "T04",
            "participantID": "P02",
            "date": "2018-10-06",
            "time": "18:49:00",
            "utterance": "웹에서 방금 테스트로"
        },
        {
            "utteranceID": "U13",
            "turnID": "T05",
            "participantID": "P01",
            "date": "2018-10-06",
            "time": "18:49:00",
            "utterance": "그럼 프로그램만 깔아서 다 채굴해놓고"
        },
        {
            "utteranceID": "U14",
            "turnID": "T06",
            "participantID": "P02",
            "date": "2018-10-06",
            "time": "18:49:00",
            "utterance": "로그인하고나서 니한테 100 보냇는데"
        },
        {
            "utteranceID": "U15",
            "turnID": "T06",
            "participantID": "P02",
            "date": "2018-10-06",
            "time": "18:50:00",
            "utterance": "따로 보안없이 바로 전송되네"
        },
        {
            "utteranceID": "U16",
            "turnID": "T07",
            "participantID": "P01",
            "date": "2018-10-06",
            "time": "18:50:00",
            "utterance": "그건 웹으로 보냄?"
        },
        {
            "utteranceID": "U17",
            "turnID": "T08",
            "participantID": "P02",
            "date": "2018-10-06",
            "time": "18:50:00",
            "utterance": "엉 ㅋㅋ"
        },
        {
            "utteranceID": "U18",
            "turnID": "T08",
            "participantID": "P02",
            "date": "2018-10-06",
            "time": "18:50:00",
            "utterance": "프로그램에선 안되고"
        },
        {
            "utteranceID": "U19",
            "turnID": "T09",
            "participantID": "P01",
            "date": "2018-10-06",
            "time": "18:50:00",
            "utterance": "프로그램은 걍 채굴만 위한 프로그램?"
        },
        {
            "utteranceID": "U20",
            "turnID": "T10",
            "participantID": "P02",
            "date": "2018-10-06",
            "time": "18:50:00",
            "utterance": "엉 ㅋㅋㅋ"
        }
    ]
}