{
    "header": {
        "dialogueInfo": {
            "dialogueID": "2a9fd6f7-70ff-594c-9bf4-5378c29fc05f",
            "numberOfParticipants": 2,
            "numberOfUtterances": 13,
            "numberOfTurns": 8,
            "source": "한국어SNS",
            "single_topic": "개인 및 관계",
            "multi_topic": [
                "안부/일상_일상공유_소문/루머"
            ]
        },
        "participantsInfo": [
            {
                "participantID": "P01",
                "gender": "여성",
                "age": "20대",
                "residentialProvince": "경상남도"
            },
            {
                "participantID": "P02",
                "gender": "여성",
                "age": "20대",
                "residentialProvince": "대전광역시"
            }
        ]
    },
    "body": [
        {
            "utteranceID": "U01",
            "turnID": "T01",
            "participantID": "P01",
            "date": "2019-11-14",
            "time": "21:47:00",
            "utterance": "회사채팅방에 주로 쓴다더라 칭그칭그가"
        },
        {
            "utteranceID": "U02",
            "turnID": "T02",
            "participantID": "P02",
            "date": "2019-11-14",
            "time": "21:47:00",
            "utterance": "내가 못쓰는구나"
        },
        {
            "utteranceID": "U03",
            "turnID": "T03",
            "participantID": "P01",
            "date": "2019-11-14",
            "time": "21:47:00",
            "utterance": "학교채팅방이나"
        },
        {
            "utteranceID": "U04",
            "turnID": "T03",
            "participantID": "P01",
            "date": "2019-11-14",
            "time": "21:47:00",
            "utterance": "응"
        },
        {
            "utteranceID": "U05",
            "turnID": "T04",
            "participantID": "P02",
            "date": "2019-11-14",
            "time": "21:47:00",
            "utterance": "그래서 방 잘못찾아서"
        },
        {
            "utteranceID": "U06",
            "turnID": "T04",
            "participantID": "P02",
            "date": "2019-11-14",
            "time": "21:47:00",
            "utterance": "헛말안할수잇는"
        },
        {
            "utteranceID": "U07",
            "turnID": "T05",
            "participantID": "P01",
            "date": "2019-11-14",
            "time": "21:47:00",
            "utterance": "응응 그런거를 이제"
        },
        {
            "utteranceID": "U08",
            "turnID": "T05",
            "participantID": "P01",
            "date": "2019-11-14",
            "time": "21:48:00",
            "utterance": "잘못보내도 되는 방과"
        },
        {
            "utteranceID": "U09",
            "turnID": "T05",
            "participantID": "P01",
            "date": "2019-11-14",
            "time": "21:48:00",
            "utterance": "안되는 방을 나누는"
        },
        {
            "utteranceID": "U10",
            "turnID": "T05",
            "participantID": "P01",
            "date": "2019-11-14",
            "time": "21:48:00",
            "utterance": "ㅇㅋㅇㅋ?"
        },
        {
            "utteranceID": "U11",
            "turnID": "T06",
            "participantID": "P02",
            "date": "2019-11-14",
            "time": "21:48:00",
            "utterance": "웅"
        },
        {
            "utteranceID": "U12",
            "turnID": "T07",
            "participantID": "P01",
            "date": "2019-11-14",
            "time": "21:48:00",
            "utterance": "웅"
        },
        {
            "utteranceID": "U13",
            "turnID": "T08",
            "participantID": "P02",
            "date": "2019-11-14",
            "time": "21:48:00",
            "utterance": "신기하다"
        }
    ]
}